{
  "$ref": "#/definitions/default.50d88764",
  "definitions": {
    "default.50d88764": {
      "title": "default.50d88764",
      "type": "object",
      "additionalProperties": {
        "additionalProperties": false,
        "type": "object",
        "properties": {
          "name": {
            "type": "string",
            "title": "name"
          },
          "description": {
            "type": "string",
            "title": "description"
          },
          "latestRelease": {
            "anyOf": [
              {
                "$ref": "#/definitions/default.Release<string>.f8908403"
              },
              {
                "enum": ["_github", "_npm"],
                "type": "string"
              }
            ],
            "title": "latestRelease"
          },
          "pageContents": {
            "anyOf": [
              {
                "type": "object",
                "properties": {
                  "html": {
                    "type": "string",
                    "title": "html"
                  },
                  "css": {
                    "type": "string",
                    "title": "css"
                  }
                },
                "defaultProperties": [],
                "additionalProperties": false
              },
              {
                "type": "string"
              }
            ],
            "title": "pageContents"
          },
          "lifespan": {
            "anyOf": [
              {
                "$ref": "#/definitions/default.Lifespan<string>.8e0a6c13"
              },
              {
                "enum": ["_github"],
                "type": "string"
              }
            ],
            "title": "lifespan"
          },
          "links": {
            "type": "array",
            "items": {
              "$ref": "#/definitions/default.Link.902513d3"
            },
            "title": "links"
          },
          "downloads": {
            "type": "array",
            "items": {
              "$ref": "#/definitions/default.Download.45c97a3c"
            },
            "title": "downloads"
          },
          "_sources": {
            "type": "object",
            "properties": {
              "github": {
                "$ref": "#/definitions/Config.3b186f31",
                "title": "github"
              },
              "npm": {
                "$ref": "#/definitions/Config.a9f67f3e",
                "title": "npm"
              }
            },
            "defaultProperties": [],
            "additionalProperties": false,
            "title": "_sources"
          }
        }
      },
      "defaultProperties": []
    },
    "default.Release<string>.f8908403": {
      "title": "default.Release<string>.f8908403",
      "type": "object",
      "properties": {
        "version": {
          "type": "string",
          "title": "version"
        },
        "timestamp": {
          "$ref": "#/definitions/Project.Release.D.36808144",
          "title": "timestamp"
        },
        "isPrerelease": {
          "type": "boolean",
          "title": "isPrerelease"
        }
      },
      "defaultProperties": [],
      "additionalProperties": false,
      "required": ["timestamp", "version"]
    },
    "Project.Release.D.36808144": {
      "title": "Project.Release.D.36808144",
      "type": "string"
    },
    "default.Lifespan<string>.8e0a6c13": {
      "title": "default.Lifespan<string>.8e0a6c13",
      "type": "object",
      "properties": {
        "begun": {
          "$ref": "#/definitions/Project.Lifespan.D.6381d366",
          "title": "begun"
        },
        "ended": {
          "$ref": "#/definitions/Project.Lifespan.D.6381d366",
          "title": "ended"
        }
      },
      "defaultProperties": [],
      "additionalProperties": false,
      "required": ["begun"]
    },
    "Project.Lifespan.D.6381d366": {
      "title": "Project.Lifespan.D.6381d366",
      "type": "string"
    },
    "default.Link.902513d3": {
      "title": "default.Link.902513d3",
      "type": "object",
      "properties": {
        "type": {
          "enum": ["github", "npm"],
          "type": "string",
          "title": "type"
        },
        "url": {
          "type": "string",
          "title": "url"
        }
      },
      "defaultProperties": [],
      "additionalProperties": false,
      "required": ["type", "url"]
    },
    "default.Download.45c97a3c": {
      "title": "default.Download.45c97a3c",
      "type": "object",
      "properties": {
        "type": {
          "type": "string",
          "enum": ["binary"],
          "title": "type"
        },
        "platform": {
          "enum": ["macos", "windows"],
          "type": "string",
          "title": "platform"
        },
        "url": {
          "type": "string",
          "title": "url"
        }
      },
      "defaultProperties": [],
      "additionalProperties": false,
      "required": ["platform", "type", "url"]
    },
    "Config.3b186f31": {
      "title": "Config.3b186f31",
      "type": "object",
      "properties": {
        "owner": {
          "type": "string",
          "title": "owner"
        },
        "name": {
          "type": "string",
          "title": "name"
        },
        "countLifespanAsStillOngoing": {
          "type": "boolean",
          "title": "countLifespanAsStillOngoing"
        }
      },
      "defaultProperties": [],
      "additionalProperties": false,
      "required": ["name", "owner"]
    },
    "Config.a9f67f3e": {
      "title": "Config.a9f67f3e",
      "type": "object",
      "properties": {
        "name": {
          "type": "string",
          "title": "name"
        }
      },
      "defaultProperties": [],
      "additionalProperties": false,
      "required": ["name"]
    }
  },
  "$schema": "http://json-schema.org/draft-07/schema#"
}
